duplicateindexer/README.MD
duplicateindexer/__init__.py
duplicateindexer/requirements.txt
duplicateindexer/thirdparty.json
duplicateindexer-0.10.dist-info/LICENSE.rst
duplicateindexer-0.10.dist-info/METADATA
duplicateindexer-0.10.dist-info/WHEEL
duplicateindexer-0.10.dist-info/top_level.txt
duplicateindexer-0.10.dist-info/RECORD
