Metadata-Version: 2.1
Name: duplicateindexer
Version: 0.10
Summary: Find duplicates in multiple lists and return their indices and values.
Home-page: https://github.com/hansalemaos/duplicateindexer
Author: Johannes Fischer
Author-email: aulasparticularesdealemaosp@gmail.com
License: MIT
Keywords: find,duplicates
Classifier: Development Status :: 4 - Beta
Classifier: Programming Language :: Python :: 3 :: Only
Classifier: Programming Language :: Python :: 3.10
Classifier: Topic :: Software Development :: Libraries :: Python Modules
Classifier: Topic :: Utilities
License-File: LICENSE.rst
Requires-Dist: hashlistdict
